stripe/__init__.py
stripe/account.py
stripe/balance.py
stripe/base.py
stripe/charge.py
stripe/customer.py
stripe/intent.py
stripe/secure.py
stripe/source.py
stripe/token.py
stripe_api-0.3.2.dist-info/LICENSE
stripe_api-0.3.2.dist-info/METADATA
stripe_api-0.3.2.dist-info/WHEEL
stripe_api-0.3.2.dist-info/top_level.txt
stripe_api-0.3.2.dist-info/RECORD
